reactor.py
examples/update_mypy_version.py
gitmultirepoupdater/__init__.py
gitmultirepoupdater/cli.py
gitmultirepoupdater/constants.py
gitmultirepoupdater/data_types.py
gitmultirepoupdater/actions/__init__.py
gitmultirepoupdater/actions/argument_parsing.py
gitmultirepoupdater/actions/clone_repositories.py
gitmultirepoupdater/actions/commit_and_push_changes.py
gitmultirepoupdater/actions/create_branch.py
gitmultirepoupdater/actions/create_pull_request.py
gitmultirepoupdater/actions/get_repository_states.py
gitmultirepoupdater/actions/run_command.py
gitmultirepoupdater/utils/__init__.py
gitmultirepoupdater/utils/argument_parsing.py
gitmultirepoupdater/utils/helpers.py
gitmultirepoupdater/utils/throttled_tasks_executor.py
git_multi_repo_updater-0.1.4.dist-info/METADATA
git_multi_repo_updater-0.1.4.dist-info/WHEEL
git_multi_repo_updater-0.1.4.dist-info/entry_points.txt
git_multi_repo_updater-0.1.4.dist-info/licenses/LICENSE
git_multi_repo_updater-0.1.4.dist-info/RECORD
