Metadata-Version: 2.1
Name: git-multi-repo-updater
Version: 0.1.4
Summary: git-multi-repo-updater is a command line tool for updating multiple GitLab or GitHub repositories with a single command.
Author-email: Albertas Gimbutas <albertasgim@gmail.com>
License-File: LICENSE
Classifier: Development Status :: 3 - Alpha
Classifier: License :: OSI Approved :: GNU Affero General Public License v3
Classifier: Natural Language :: English
Classifier: Operating System :: OS Independent
Classifier: Programming Language :: Python
Classifier: Programming Language :: Python :: 3.8
Classifier: Programming Language :: Python :: 3.9
Classifier: Programming Language :: Python :: 3.10
Classifier: Programming Language :: Python :: 3.11
Requires-Python: >=3.8
Requires-Dist: gitpython>=3.1.29
Requires-Dist: httpx>=0.23.1
